xiangqi_board/__init__.py
xiangqi_board/__main__.py
xiangqi_board/painter.py
xiangqi_setup/__init__.py
xiangqi_setup/__main__.py
xiangqi_setup/annotations.py
xiangqi_setup/compose.py
xiangqi_setup/default_setup.py
xiangqi_setup/license.py
xiangqi_setup/parties.py
xiangqi_setup/pieces.py
xiangqi_setup/version.py
xiangqi_setup/file_formats/__init__.py
xiangqi_setup/file_formats/annofen.py
xiangqi_setup/file_formats/fen.py
xiangqi_setup/file_formats/wxf.py
xiangqi_setup/file_formats/xay.py
xiangqi_setup/file_formats/tests/__init__.py
xiangqi_setup/file_formats/tests/test_wxf.py
xiangqi_setup/themes/__init__.py
xiangqi_setup/themes/annotations/__init__.py
xiangqi_setup/themes/annotations/colors_alpha/LICENSE.json
xiangqi_setup/themes/annotations/colors_alpha/__init__.py
xiangqi_setup/themes/annotations/colors_alpha/arrow_minus_1_minus_1.svg
xiangqi_setup/themes/annotations/colors_alpha/arrow_minus_1_minus_2.svg
xiangqi_setup/themes/annotations/colors_alpha/arrow_minus_1_plus_0.svg
xiangqi_setup/themes/annotations/colors_alpha/arrow_minus_1_plus_1.svg
xiangqi_setup/themes/annotations/colors_alpha/arrow_minus_1_plus_2.svg
xiangqi_setup/themes/annotations/colors_alpha/arrow_minus_2_minus_1.svg
xiangqi_setup/themes/annotations/colors_alpha/arrow_minus_2_minus_2.svg
xiangqi_setup/themes/annotations/colors_alpha/arrow_minus_2_plus_0.svg
xiangqi_setup/themes/annotations/colors_alpha/arrow_minus_2_plus_1.svg
xiangqi_setup/themes/annotations/colors_alpha/arrow_minus_2_plus_2.svg
xiangqi_setup/themes/annotations/colors_alpha/arrow_minus_3_plus_0.svg
xiangqi_setup/themes/annotations/colors_alpha/arrow_minus_4_plus_0.svg
xiangqi_setup/themes/annotations/colors_alpha/arrow_minus_5_plus_0.svg
xiangqi_setup/themes/annotations/colors_alpha/arrow_minus_6_plus_0.svg
xiangqi_setup/themes/annotations/colors_alpha/arrow_minus_7_plus_0.svg
xiangqi_setup/themes/annotations/colors_alpha/arrow_minus_8_plus_0.svg
xiangqi_setup/themes/annotations/colors_alpha/arrow_plus_0_minus_1.svg
xiangqi_setup-2.2.0.dist-info/METADATA
xiangqi_setup-2.2.0.dist-info/WHEEL
xiangqi_setup-2.2.0.dist-info/entry_points.txt
xiangqi_setup-2.2.0.dist-info/top_level.txt
xiangqi_setup-2.2.0.dist-info/RECORD
