Metadata-Version: 2.1
Name: xiangqi-setup
Version: 2.2.0
Summary: Command line tool to generate razor-sharp Xiangqi (Chinese chess) setup graphics
Home-page: https://github.com/hartwork/xiangqi-setup
Download-URL: https://github.com/hartwork/xiangqi-setup/archive/2.2.0.tar.gz
Author: Sebastian Pipping
Author-email: sebastian@pipping.org
License: GNU Affero General Public License version 3.0 or later
Classifier: Development Status :: 4 - Beta
Classifier: Environment :: Console
Classifier: Intended Audience :: Education
Classifier: Intended Audience :: Other Audience
Classifier: License :: OSI Approved :: GNU Affero General Public License v3 or later (AGPLv3+)
Classifier: Natural Language :: English
Classifier: Programming Language :: Python
Classifier: Programming Language :: Python :: 3
Classifier: Programming Language :: Python :: 3.8
Classifier: Programming Language :: Python :: 3.9
Classifier: Programming Language :: Python :: 3.10
Classifier: Programming Language :: Python :: 3.11
Classifier: Programming Language :: Python :: 3 :: Only
Classifier: Topic :: Artistic Software
Classifier: Topic :: Games/Entertainment :: Board Games
Classifier: Topic :: Multimedia :: Graphics
Classifier: Topic :: Printing
Classifier: Topic :: Utilities
Requires-Python: >=3.8
Requires-Dist: pyyaml
Requires-Dist: svgutils (==0.3.4)
Provides-Extra: tests
Requires-Dist: parameterized ; extra == 'tests'
Requires-Dist: pytest ; extra == 'tests'
